toon3d/__init__.py
toon3d/toon3d_config.py
toon3d/toon3d_datamanager.py
toon3d/toon3d_dataparser.py
toon3d/toon3d_model.py
toon3d/toon3d_pipeline.py
toon3d/configs/prompts.py
toon3d/generative/marigold.py
toon3d/scripts/colmap_with_corrs.py
toon3d/scripts/download_data.py
toon3d/scripts/process_data.py
toon3d/scripts/render.py
toon3d/scripts/run.py
toon3d/scripts/server.py
toon3d/scripts/viser_vis.py
toon3d/utils/camera_utils.py
toon3d/utils/colmap_database.py
toon3d/utils/convert_points.py
toon3d/utils/depth_utils.py
toon3d/utils/draw_utils.py
toon3d/utils/image_processing_utils.py
toon3d/utils/io_utils.py
toon3d/utils/losses.py
toon3d/utils/novel_view_samplers.py
toon3d/utils/viser_utils.py
toon3d/warp/arap_utils.py
toon3d/warp/warp_mesh.py
toon3d-labeler/node_modules/flatted/python/flatted.py
toon3d-labeler/node_modules/flatted/python/test.py
toon3d-spaces/app.py
toon3d-0.0.5.dist-info/METADATA
toon3d-0.0.5.dist-info/WHEEL
toon3d-0.0.5.dist-info/entry_points.txt
toon3d-0.0.5.dist-info/top_level.txt
toon3d-0.0.5.dist-info/RECORD
